Workbook

Sheet Cómo usarlo
A1: CAPÍTULO 12 · MATERIAL PRÁCTICO
A2: Cuadro de mando mensual
A3: Material complementario de «Vende más y trabaja menos»
A6: 1. Datos
B7: Escribe el primer mes en la celda amarilla clara y, cada mes, los datos de esa columna. Saca los datos de tus herramientas, no los teclees de memoria: la web, el CRM, la plataforma de email y la de atención al cliente.
B8: No hace falta rellenarlo todo. Empieza por los datos de tus tres o cuatro métricas elegidas.
A10: 2. Métricas
B11: La hoja «Métricas» calcula las diez métricas del libro para cada mes, siempre con la misma fórmula.
A13: 3. Cuadro de mando
B14: Elige el número del mes que vas a revisar, escribe el objetivo de cada métrica y la hoja te muestra el dato del mes, el del mes anterior, la tendencia y si cumples el objetivo.
B15: La columna más importante es la última: cada métrica que se desvía de su objetivo debe salir de la reunión mensual con una acción concreta, un responsable y una fecha.
B16: Vigila la relación entre el valor de vida del cliente y su coste de adquisición: si se acercan, estás pagando demasiado por cada cliente.
A18: Orden del día de la reunión mensual de una hora
B19: Diez minutos: repaso del cuadro de mando y de las acciones del mes anterior.
B20: Veinte minutos: análisis de las dos o tres desviaciones más importantes y de sus causas.
B21: Veinte minutos: decisiones: qué ajustamos, qué probamos con una prueba A/B, qué dejamos de hacer.
B22: Diez minutos: reparto de acciones con responsable y fecha, y un logro que celebrar.
B24: Las celdas en amarillo claro son para rellenar. Las demás se calculan solas.
B26: Material complementario del libro «Vende más y trabaja menos», de Jacob Ruiz. © 2026 Jacob Ruiz. Uso libre en tu empresa; no se permite su venta ni su distribución como material propio.

Sheet Datos
A1: CAPÍTULO 12 · MATERIAL PRÁCTICO
A2: Datos de cada mes
A3: Saca los datos de tus herramientas y escríbelos en su mes
A4: Primer mes (escribe una fecha de ese mes)
A5: Dato | B5: =IF($B$4="","Mes 1",$B$4) | C5: =IF($B$4="","Mes 2",EDATE($B$4,1)) | D5: =IF($B$4="","Mes 3",EDATE($B$4,2)) | E5: =IF($B$4="","Mes 4",EDATE($B$4,3)) | F5: =IF($B$4="","Mes 5",EDATE($B$4,4)) | G5: =IF($B$4="","Mes 6",EDATE($B$4,5)) | H5: =IF($B$4="","Mes 7",EDATE($B$4,6)) | I5: =IF($B$4="","Mes 8",EDATE($B$4,7)) | J5: =IF($B$4="","Mes 9",EDATE($B$4,8)) | K5: =IF($B$4="","Mes 10",EDATE($B$4,9)) | L5: =IF($B$4="","Mes 11",EDATE($B$4,10)) | M5: =IF($B$4="","Mes 12",EDATE($B$4,11))
A6: Visitas a la web
A7: Contactos nuevos
A8: Inversión en captación (€)
A9: Correos entregados
A10: Clics en los correos
A11: Presupuestos enviados
A12: Ventas ganadas de esos presupuestos
A13: Ingresos (€)
A14: Número de ventas
A15: Inversión total en marketing y ventas (€)
A16: Clientes nuevos
A17: Margen medio anual por cliente (€)
... A24: Tiempo medio de primera respuesta (horas)

Sheet Métricas
A1: CAPÍTULO 12 · MATERIAL PRÁCTICO
A2: Las diez métricas, mes a mes
A3: Se calculan solas a partir de la hoja «Datos»
A5: Métrica | B5: =Datos!B5 | C5: =Datos!C5 | D5: =Datos!D5 | E5: =Datos!E5 | F5: =Datos!F5 | G5: =Datos!G5 | H5: =Datos!H5 | I5: =Datos!I5 | ... M5: =Datos!M5
A6: Tasa de conversión de la web | B6: =IF(OR(Datos!B7="",Datos!B6="",N(Datos!B6)=0),"",Datos!B7/Datos!B6) | C6: =IF(OR(Datos!C7="",Datos!C6="",N(Datos!C6)=0),"",Datos!C7/Datos!C6) | D6: =IF(OR(Datos!D7="",Datos!D6="",N(Datos!D6)=0),"",Datos!D7/Datos!D6) | E6: =IF(OR(Datos!E7="",Datos!E6="",N(Datos!E6)=0),"",Datos!E7/Datos!E6) | F6: =IF(OR(Datos!F7="",Datos!F6="",N(Datos!F6)=0),"",Datos!F7/Datos!F6) | G6: =IF(OR(Datos!G7="",Datos!G6="",N(Datos!G6)=0),"",Datos!G7/Datos!G6) | H6: =IF(OR(Datos!H7="",Datos!H6="",N(Datos!H6)=0),"",Datos!H7/Datos!H6) | I6: =IF(OR(Datos!I7="",Datos!I6="",N(Datos!I6)=0),"",Datos!I7/Datos!I6) | ... M6: =IF(OR(Datos!M7="",Datos!M6="",N(Datos!M6)=0),"",Datos!M7/Datos!M6)
A7: Coste por contacto | B7: =IF(OR(Datos!B8="",Datos!B7="",N(Datos!B7)=0),"",Datos!B8/Datos!B7) | C7: =IF(OR(Datos!C8="",Datos!C7="",N(Datos!C7)=0),"",Datos!C8/Datos!C7) | D7: =IF(OR(Datos!D8="",Datos!D7="",N(Datos!D7)=0),"",Datos!D8/Datos!D7) | E7: =IF(OR(Datos!E8="",Datos!E7="",N(Datos!E7)=0),"",Datos!E8/Datos!E7) | F7: =IF(OR(Datos!F8="",Datos!F7="",N(Datos!F7)=0),"",Datos!F8/Datos!F7) | G7: =IF(OR(Datos!G8="",Datos!G7="",N(Datos!G7)=0),"",Datos!G8/Datos!G7) | H7: =IF(OR(Datos!H8="",Datos!H7="",N(Datos!H7)=0),"",Datos!H8/Datos!H7) | I7: =IF(OR(Datos!I8="",Datos!I7="",N(Datos!I7)=0),"",Datos!I8/Datos!I7) | ... M7: =IF(OR(Datos!M8="",Datos!M7="",N(Datos!M7)=0),"",Datos!M8/Datos!M7)
A8: Tasa de clics del email | B8: =IF(OR(Datos!B10="",Datos!B9="",N(Datos!B9)=0),"",Datos!B10/Datos!B9) | C8: =IF(OR(Datos!C10="",Datos!C9="",N(Datos!C9)=0),"",Datos!C10/Datos!C9) | D8: =IF(OR(Datos!D10="",Datos!D9="",N(Datos!D9)=0),"",Datos!D10/Datos!D9) | E8: =IF(OR(Datos!E10="",Datos!E9="",N(Datos!E9)=0),"",Datos!E10/Datos!E9) | F8: =IF(OR(Datos!F10="",Datos!F9="",N(Datos!F9)=0),"",Datos!F10/Datos!F9) | G8: =IF(OR(Datos!G10="",Datos!G9="",N(Datos!G9)=0),"",Datos!G10/Datos!G9) | H8: =IF(OR(Datos!H10="",Datos!H9="",N(Datos!H9)=0),"",Datos!H10/Datos!H9) | I8: =IF(OR(Datos!I10="",Datos!I9="",N(Datos!I9)=0),"",Datos!I10/Datos!I9) | ... M8: =IF(OR(Datos!M10="",Datos!M9="",N(Datos!M9)=0),"",Datos!M10/Datos!M9)
A9: Tasa de cierre | B9: =IF(OR(Datos!B12="",Datos!B11="",N(Datos!B11)=0),"",Datos!B12/Datos!B11) | C9: =IF(OR(Datos!C12="",Datos!C11="",N(Datos!C11)=0),"",Datos!C12/Datos!C11) | D9: =IF(OR(Datos!D12="",Datos!D11="",N(Datos!D11)=0),"",Datos!D12/Datos!D11) | E9: =IF(OR(Datos!E12="",Datos!E11="",N(Datos!E11)=0),"",Datos!E12/Datos!E11) | F9: =IF(OR(Datos!F12="",Datos!F11="",N(Datos!F11)=0),"",Datos!F12/Datos!F11) | G9: =IF(OR(Datos!G12="",Datos!G11="",N(Datos!G11)=0),"",Datos!G12/Datos!G11) | H9: =IF(OR(Datos!H12="",Datos!H11="",N(Datos!H11)=0),"",Datos!H12/Datos!H11) | I9: =IF(OR(Datos!I12="",Datos!I11="",N(Datos!I11)=0),"",Datos!I12/Datos!I11) | ... M9: =IF(OR(Datos!M12="",Datos!M11="",N(Datos!M11)=0),"",Datos!M12/Datos!M11)
A10: Valor medio por venta | B10: =IF(OR(Datos!B13="",Datos!B14="",N(Datos!B14)=0),"",Datos!B13/Datos!B14) | C10: =IF(OR(Datos!C13="",Datos!C14="",N(Datos!C14)=0),"",Datos!C13/Datos!C14) | D10: =IF(OR(Datos!D13="",Datos!D14="",N(Datos!D14)=0),"",Datos!D13/Datos!D14) | E10: =IF(OR(Datos!E13="",Datos!E14="",N(Datos!E14)=0),"",Datos!E13/Datos!E14) | F10: =IF(OR(Datos!F13="",Datos!F14="",N(Datos!F14)=0),"",Datos!F13/Datos!F14) | G10: =IF(OR(Datos!G13="",Datos!G14="",N(Datos!G14)=0),"",Datos!G13/Datos!G14) | H10: =IF(OR(Datos!H13="",Datos!H14="",N(Datos!H14)=0),"",Datos!H13/Datos!H14) | I10: =IF(OR(Datos!I13="",Datos!I14="",N(Datos!I14)=0),"",Datos!I13/Datos!I14) | ... M10: =IF(OR(Datos!M13="",Datos!M14="",N(Datos!M14)=0),"",Datos!M13/Datos!M14)
A11: Coste de adquisición de cliente | B11: =IF(OR(Datos!B15="",Datos!B16="",N(Datos!B16)=0),"",Datos!B15/Datos!B16) | C11: =IF(OR(Datos!C15="",Datos!C16="",N(Datos!C16)=0),"",Datos!C15/Datos!C16) | D11: =IF(OR(Datos!D15="",Datos!D16="",N(Datos!D16)=0),"",Datos!D15/Datos!D16) | E11: =IF(OR(Datos!E15="",Datos!E16="",N(Datos!E16)=0),"",Datos!E15/Datos!E16) | F11: =IF(OR(Datos!F15="",Datos!F16="",N(Datos!F16)=0),"",Datos!F15/Datos!F16) | G11: =IF(OR(Datos!G15="",Datos!G16="",N(Datos!G16)=0),"",Datos!G15/Datos!G16) | H11: =IF(OR(Datos!H15="",Datos!H16="",N(Datos!H16)=0),"",Datos!H15/Datos!H16) | I11: =IF(OR(Datos!I15="",Datos!I16="",N(Datos!I16)=0),"",Datos!I15/Datos!I16) | ... M11: =IF(OR(Datos!M15="",Datos!M16="",N(Datos!M16)=0),"",Datos!M15/Datos!M16)
A12: Valor de vida del cliente | B12: =IF(OR(Datos!B17="",Datos!B18=""),"",Datos!B17*Datos!B18) | C12: =IF(OR(Datos!C17="",Datos!C18=""),"",Datos!C17*Datos!C18) | D12: =IF(OR(Datos!D17="",Datos!D18=""),"",Datos!D17*Datos!D18) | E12: =IF(OR(Datos!E17="",Datos!E18=""),"",Datos!E17*Datos!E18) | F12: =IF(OR(Datos!F17="",Datos!F18=""),"",Datos!F17*Datos!F18) | G12: =IF(OR(Datos!G17="",Datos!G18=""),"",Datos!G17*Datos!G18) | H12: =IF(OR(Datos!H17="",Datos!H18=""),"",Datos!H17*Datos!H18) | I12: =IF(OR(Datos!I17="",Datos!I18=""),"",Datos!I17*Datos!I18) | ... M12: =IF(OR(Datos!M17="",Datos!M18=""),"",Datos!M17*Datos!M18)
A13: Tasa de abandono | B13: =IF(OR(Datos!B20="",Datos!B19="",N(Datos!B19)=0),"",Datos!B20/Datos!B19) | C13: =IF(OR(Datos!C20="",Datos!C19="",N(Datos!C19)=0),"",Datos!C20/Datos!C19) | D13: =IF(OR(Datos!D20="",Datos!D19="",N(Datos!D19)=0),"",Datos!D20/Datos!D19) | E13: =IF(OR(Datos!E20="",Datos!E19="",N(Datos!E19)=0),"",Datos!E20/Datos!E19) | F13: =IF(OR(Datos!F20="",Datos!F19="",N(Datos!F19)=0),"",Datos!F20/Datos!F19) | G13: =IF(OR(Datos!G20="",Datos!G19="",N(Datos!G19)=0),"",Datos!G20/Datos!G19) | H13: =IF(OR(Datos!H20="",Datos!H19="",N(Datos!H19)=0),"",Datos!H20/Datos!H19) | I13: =IF(OR(Datos!I20="",Datos!I19="",N(Datos!I19)=0),"",Datos!I20/Datos!I19) | ... M13: =IF(OR(Datos!M20="",Datos!M19="",N(Datos!M19)=0),"",Datos!M20/Datos!M19)
A14: NPS | B14: =IF(OR(Datos!B22="",Datos!B23="",Datos!B21="",N(Datos!B21)=0),"",ROUND((Datos!B22-Datos!B23)/Datos!B21*100,0)) | C14: =IF(OR(Datos!C22="",Datos!C23="",Datos!C21="",N(Datos!C21)=0),"",ROUND((Datos!C22-Datos!C23)/Datos!C21*100,0)) | D14: =IF(OR(Datos!D22="",Datos!D23="",Datos!D21="",N(Datos!D21)=0),"",ROUND((Datos!D22-Datos!D23)/Datos!D21*100,0)) | E14: =IF(OR(Datos!E22="",Datos!E23="",Datos!E21="",N(Datos!E21)=0),"",ROUND((Datos!E22-Datos!E23)/Datos!E21*100,0)) | F14: =IF(OR(Datos!F22="",Datos!F23="",Datos!F21="",N(Datos!F21)=0),"",ROUND((Datos!F22-Datos!F23)/Datos!F21*100,0)) | G14: =IF(OR(Datos!G22="",Datos!G23="",Datos!G21="",N(Datos!G21)=0),"",ROUND((Datos!G22-Datos!G23)/Datos!G21*100,0)) | H14: =IF(OR(Datos!H22="",Datos!H23="",Datos!H21="",N(Datos!H21)=0),"",ROUND((Datos!H22-Datos!H23)/Datos!H21*100,0)) | I14: =IF(OR(Datos!I22="",Datos!I23="",Datos!I21="",N(Datos!I21)=0),"",ROUND((Datos!I22-Datos!I23)/Datos!I21*100,0)) | ... M14: =IF(OR(Datos!M22="",Datos!M23="",Datos!M21="",N(Datos!M21)=0),"",ROUND((Datos!M22-Datos!M23)/Datos!M21*100,0))
A15: Tiempo de primera respuesta (horas) | B15: =IF(OR(Datos!B24=""),"",Datos!B24) | C15: =IF(OR(Datos!C24=""),"",Datos!C24) | D15: =IF(OR(Datos!D24=""),"",Datos!D24) | E15: =IF(OR(Datos!E24=""),"",Datos!E24) | F15: =IF(OR(Datos!F24=""),"",Datos!F24) | G15: =IF(OR(Datos!G24=""),"",Datos!G24) | H15: =IF(OR(Datos!H24=""),"",Datos!H24) | I15: =IF(OR(Datos!I24=""),"",Datos!I24) | ... M15: =IF(OR(Datos!M24=""),"",Datos!M24)
A16: Valor de vida ÷ coste de adquisición | B16: =IF(OR(B12="",N(B11)=0),"",B12/B11) | C16: =IF(OR(C12="",N(C11)=0),"",C12/C11) | D16: =IF(OR(D12="",N(D11)=0),"",D12/D11) | E16: =IF(OR(E12="",N(E11)=0),"",E12/E11) | F16: =IF(OR(F12="",N(F11)=0),"",F12/F11) | G16: =IF(OR(G12="",N(G11)=0),"",G12/G11) | H16: =IF(OR(H12="",N(H11)=0),"",H12/H11) | I16: =IF(OR(I12="",N(I11)=0),"",I12/I11) | ... M16: =IF(OR(M12="",N(M11)=0),"",M12/M11)
A17: Si esta relación se acerca a 1, estás pagando demasiado por cada cliente.

Sheet Cuadro de mando
A1: CAPÍTULO 12 · MATERIAL PRÁCTICO
A2: Tu cuadro de mando de una página
A3: Cada desviación sale de la reunión con una acción, un responsable y una fecha
A4: Mes que revisas (número del 1 al 12) | B4: 1 | C4: =INDEX(Datos!B5:M5,B4)
A6: Métrica | B6: Mejor si es | C6: Objetivo | D6: Este mes | E6: Mes anterior | F6: Tendencia | G6: Estado | H6: Acción decidida | I6: Responsable | J6: Fecha
A7: Tasa de conversión de la web | B7: Más alto | D7: =INDEX(Métricas!B6:M6,$B$4) | E7: =IF($B$4=1,"",INDEX(Métricas!B6:M6,$B$4-1)) | F7: =IF(OR(D7="",E7=""),"",IF(D7>E7,"Sube",IF(D7<E7,"Baja","Igual"))) | G7: =IF(OR(C7="",D7=""),"",IF(D7>=C7,"En objetivo","Desviada"))
A8: Coste por contacto | B8: Más bajo | D8: =INDEX(Métricas!B7:M7,$B$4) | E8: =IF($B$4=1,"",INDEX(Métricas!B7:M7,$B$4-1)) | F8: =IF(OR(D8="",E8=""),"",IF(D8>E8,"Sube",IF(D8<E8,"Baja","Igual"))) | G8: =IF(OR(C8="",D8=""),"",IF(D8<=C8,"En objetivo","Desviada"))
A9: Tasa de clics del email | B9: Más alto | D9: =INDEX(Métricas!B8:M8,$B$4) | E9: =IF($B$4=1,"",INDEX(Métricas!B8:M8,$B$4-1)) | F9: =IF(OR(D9="",E9=""),"",IF(D9>E9,"Sube",IF(D9<E9,"Baja","Igual"))) | G9: =IF(OR(C9="",D9=""),"",IF(D9>=C9,"En objetivo","Desviada"))
A10: Tasa de cierre | B10: Más alto | D10: =INDEX(Métricas!B9:M9,$B$4) | E10: =IF($B$4=1,"",INDEX(Métricas!B9:M9,$B$4-1)) | F10: =IF(OR(D10="",E10=""),"",IF(D10>E10,"Sube",IF(D10<E10,"Baja","Igual"))) | G10: =IF(OR(C10="",D10=""),"",IF(D10>=C10,"En objetivo","Desviada"))
A11: Valor medio por venta | B11: Más alto | D11: =INDEX(Métricas!B10:M10,$B$4) | E11: =IF($B$4=1,"",INDEX(Métricas!B10:M10,$B$4-1)) | F11: =IF(OR(D11="",E11=""),"",IF(D11>E11,"Sube",IF(D11<E11,"Baja","Igual"))) | G11: =IF(OR(C11="",D11=""),"",IF(D11>=C11,"En objetivo","Desviada"))
A12: Coste de adquisición de cliente | B12: Más bajo | D12: =INDEX(Métricas!B11:M11,$B$4) | E12: =IF($B$4=1,"",INDEX(Métricas!B11:M11,$B$4-1)) | F12: =IF(OR(D12="",E12=""),"",IF(D12>E12,"Sube",IF(D12<E12,"Baja","Igual"))) | G12: =IF(OR(C12="",D12=""),"",IF(D12<=C12,"En objetivo","Desviada"))
A13: Valor de vida del cliente | B13: Más alto | D13: =INDEX(Métricas!B12:M12,$B$4) | E13: =IF($B$4=1,"",INDEX(Métricas!B12:M12,$B$4-1)) | F13: =IF(OR(D13="",E13=""),"",IF(D13>E13,"Sube",IF(D13<E13,"Baja","Igual"))) | G13: =IF(OR(C13="",D13=""),"",IF(D13>=C13,"En objetivo","Desviada"))
A14: Tasa de abandono | B14: Más bajo | D14: =INDEX(Métricas!B13:M13,$B$4) | E14: =IF($B$4=1,"",INDEX(Métricas!B13:M13,$B$4-1)) | F14: =IF(OR(D14="",E14=""),"",IF(D14>E14,"Sube",IF(D14<E14,"Baja","Igual"))) | G14: =IF(OR(C14="",D14=""),"",IF(D14<=C14,"En objetivo","Desviada"))
A15: NPS | B15: Más alto | D15: =INDEX(Métricas!B14:M14,$B$4) | E15: =IF($B$4=1,"",INDEX(Métricas!B14:M14,$B$4-1)) | F15: =IF(OR(D15="",E15=""),"",IF(D15>E15,"Sube",IF(D15<E15,"Baja","Igual"))) | G15: =IF(OR(C15="",D15=""),"",IF(D15>=C15,"En objetivo","Desviada"))
A16: Tiempo de primera respuesta (horas) | B16: Más bajo | D16: =INDEX(Métricas!B15:M15,$B$4) | E16: =IF($B$4=1,"",INDEX(Métricas!B15:M15,$B$4-1)) | F16: =IF(OR(D16="",E16=""),"",IF(D16>E16,"Sube",IF(D16<E16,"Baja","Igual"))) | G16: =IF(OR(C16="",D16=""),"",IF(D16<=C16,"En objetivo","Desviada"))
A18: Valor de vida ÷ coste de adquisición | D18: =INDEX(Métricas!B16:M16,$B$4)
A20: Cómo se calcula cada métrica
A21: Tasa de conversión de la web | B21: Contactos ÷ visitas × 100
A22: Coste por contacto | B22: Inversión en captación ÷ contactos conseguidos
A23: Tasa de clics del email | B23: Clics ÷ correos entregados × 100
A24: Tasa de cierre | B24: Ventas ganadas ÷ presupuestos enviados × 100
A25: Valor medio por venta | B25: Ingresos ÷ número de ventas
A26: Coste de adquisición de cliente | B26: Inversión total en marketing y ventas ÷ clientes nuevos
A27: Valor de vida del cliente | B27: Margen medio anual por cliente × años medios de relación
A28: Tasa de abandono | B28: Clientes perdidos en el periodo ÷ clientes al inicio × 100
A29: NPS | B29: % de promotores − % de detractores
A30: Tiempo de primera respuesta (horas) | B30: Tiempo medio entre la consulta y la primera respuesta
